move_imports.py
move_imports-0.4.dist-info/LICENSE
move_imports-0.4.dist-info/METADATA
move_imports-0.4.dist-info/WHEEL
move_imports-0.4.dist-info/entry_points.txt
move_imports-0.4.dist-info/top_level.txt
move_imports-0.4.dist-info/RECORD
