Metadata-Version: 2.1
Name: move-imports
Version: 0.4
Summary: Refactor modules to move import statements to the header
Home-page: https://github.com/mgaitan/move-imports
Author: Martín Gaitán
Author-email: gaitan@gmail.com
License: MIT
Keywords: ast,refactor
Platform: UNKNOWN
Classifier: Development Status :: 2 - Pre-Alpha
Classifier: Intended Audience :: Developers
Classifier: License :: OSI Approved :: BSD License
Classifier: Natural Language :: English
Classifier: Programming Language :: Python :: 3.6
Requires-Dist: isort
